nth_py/__init__.py
nth_py/nth.py
nth_py-0.0.2.dist-info/METADATA
nth_py-0.0.2.dist-info/WHEEL
nth_py-0.0.2.dist-info/entry_points.txt
nth_py-0.0.2.dist-info/top_level.txt
nth_py-0.0.2.dist-info/zip-safe
nth_py-0.0.2.dist-info/RECORD
