Metadata-Version: 2.1
Name: nth-py
Version: 0.0.2
Summary: Return or exclude the nth item via stdin
Home-page: https://alexdelorenzo.dev
Author: Alex DeLorenzo
License: AGPL-3.0
Platform: UNKNOWN
Requires-Python: >=3.6
Requires-Dist: click
